apiutil/__init__.py
apiutil/_metadata.py
apiutil/endpoints/__init__.py
apiutil/endpoints/_adhoc.py
apiutil/endpoints/_constants.py
apiutil/endpoints/api_config.py
apiutil/endpoints/apis.py
apiutil/endpoints/config.py
apiutil/endpoints/endpoints.py
apiutil/endpoints/environments.py
apiutil/endpoints/hosts.py
apiutil/endpoints/gui/__init__.py
apiutil/endpoints/gui/frame/__init__.py
apiutil/endpoints/gui/frame/api.py
apiutil/endpoints/gui/frame/apis.py
apiutil/endpoints/gui/frame/config.py
apiutil/endpoints/gui/frame/endpoint.py
apiutil/endpoints/gui/frame/endpoints.py
apiutil/endpoints/gui/frame/environment.py
apiutil/endpoints/gui/frame/environments.py
apiutil/endpoints/gui/frame/host.py
apiutil/endpoints/gui/frame/hosts.py
apiutil/endpoints/gui/window/__init__.py
apiutil/endpoints/gui/window/api.py
apiutil/endpoints/gui/window/apis.py
apiutil/endpoints/gui/window/config.py
apiutil/endpoints/gui/window/endpoint.py
apiutil/endpoints/gui/window/endpoints.py
apiutil/endpoints/gui/window/environment.py
apiutil/endpoints/gui/window/environments.py
apiutil/endpoints/gui/window/host.py
apiutil/endpoints/gui/window/hosts.py
apiutil/json_api/__init__.py
apiutil/json_api/class_creator.py
apiutil/json_api/exceptions.py
apiutil/json_api/properties.py
apiutil/json_api/request_response.py
apiutil/resources/__init__.py
apiutil/resources/schema/__init__.py
apiutil/resources/schema/api_config.json
apiutil/resources/schema/endpoint_config.json
apiutil/resources/schema/environment_config.json
apiutil/resources/schema/host_config.json
apiutil/resources/templates/__init__.py
apiutil/resources/templates/api_config.yaml
apiutil/resources/templates/endpoint_config.yaml
apiutil/resources/templates/environment_config.yaml
apiutil/resources/templates/host_config.yaml
apiutil/support/__init__.py
apiutil/support/_adhoc.py
apiutil/support/_exceptions.py
apiutil/support/api_support_cache.py
apiutil/support/api_support_layer.py
apiutil/support/apis/__init__.py
apiutil-1.9.6.dist-info/LICENSE.txt
apiutil-1.9.6.dist-info/METADATA
apiutil-1.9.6.dist-info/WHEEL
apiutil-1.9.6.dist-info/entry_points.txt
apiutil-1.9.6.dist-info/top_level.txt
apiutil-1.9.6.dist-info/RECORD
